kscore/__init__.py
kscore/auth.py
kscore/client.py
kscore/compat.py
kscore/config.py
kscore/configloader.py
kscore/credentials.py
kscore/domain.py
kscore/endpoint.py
kscore/exceptions.py
kscore/handlers.py
kscore/hooks.py
kscore/ket.py
kscore/kls.py
kscore/ksrequest.py
kscore/kvs.py
kscore/loaders.py
kscore/model.py
kscore/offline.py
kscore/paginate.py
kscore/parsers.py
kscore/regions.py
kscore/response.py
kscore/retryhandler.py
kscore/serialize.py
kscore/session.py
kscore/signers.py
kscore/stub.py
kscore/translate.py
kscore/utils.py
kscore/validate.py
kscore/waiter.py
kscore/data/_retry.yaml
kscore/data/endpoints.yaml
kscore/data/bill/2018-06-01/service-2.yaml
kscore/data/bill-union/2020-01-01/service-2.yaml
kscore/data/bws/2016-03-04/service-2.yaml
kscore/data/cdn/2016-09-01/service-2.yaml
kscore/data/cdnv2/2018-01-01/service-2.yaml
kscore/data/contact/2021-07-08/service-2.yaml
kscore/data/dns/2016-06-07/service-2.yaml
kscore/data/ebs/2016-03-04/service-2.yaml
kscore/data/eip/2016-03-04/service-2.yaml
kscore/data/epc/2015-11-01/service-2.yaml
kscore/data/iam/2015-11-01/service-2.yaml
kscore/data/kce/2019-08-06/service-2.yaml
kscore/data/kcev2/2020-12-31/service-2.yaml
kscore/data/kcm/2016-03-04/service-2.yaml
kscore/data/kcs/2016-07-01/service-2.yaml
kscore/data/kcsv2/2017-04-01/service-2.yaml
kscore/data/kec/2016-03-04/service-2.yaml
kscore/data/ket/2017-01-01/service-2.yaml
kscore/data/kingpay/V1/service-2.yaml
kscore/data/kis/2018-09-01/service-2.yaml
kscore/data/kkms/2016-03-04/service-2.yaml
kscore/data/kls/2017-01-01/service-2.yaml
kscore/data/kog/2016-08-08/service-2.yaml
kscore/data/krds/2016-07-01/service-2.yaml
kscore/data/krtpay/2019-07-19/service-2.yaml
kscore/data/kvs/2017-01-01/service-2.yaml
kscore/data/mongodb/2017-01-01/service-2.yaml
kscore/data/monitor/2010-05-25/service-2.yaml
kscore/data/monitor/2021-01-01/service-2.yaml
kscore/data/monitorv2/2021-01-01/service-2.yaml
kscore/data/offline/2016-09-19/service-2.yaml
ksc_sdk_python-1.3.58.dist-info/LICENSE.txt
ksc_sdk_python-1.3.58.dist-info/METADATA
ksc_sdk_python-1.3.58.dist-info/NOTICE
ksc_sdk_python-1.3.58.dist-info/WHEEL
ksc_sdk_python-1.3.58.dist-info/top_level.txt
ksc_sdk_python-1.3.58.dist-info/RECORD
