Metadata-Version: 2.1
Name: ksc-sdk-python
Version: 1.3.58
Summary: Low-level, data-driven core of ksc.
Home-page: https://github.com/KscSDK/ksc-sdk-python
Author: liuyichen,xuyaming,ksc_online_sdk
Author-email: ksc_sdk@kingsoft.com,xuyaming@kingsoft.com,ksc_online_sdk@kingsoft.com
License: Apache License 2.0
Platform: UNKNOWN
Classifier: Development Status :: 5 - Production/Stable
Classifier: Intended Audience :: Developers
Classifier: Intended Audience :: System Administrators
Classifier: Natural Language :: English
Classifier: License :: OSI Approved :: Apache Software License
Classifier: Programming Language :: Python
Classifier: Programming Language :: Python :: 2.6
Classifier: Programming Language :: Python :: 2.7
Classifier: Programming Language :: Python :: 3
Classifier: Programming Language :: Python :: 3.3
Classifier: Programming Language :: Python :: 3.4
Classifier: Programming Language :: Python :: 3.5
Classifier: Programming Language :: Python :: 3.6
Classifier: Programming Language :: Python :: 3.7
Classifier: Programming Language :: Python :: 3.8
Requires-Dist: jmespath (<1.0.0,>=0.7.1)
Requires-Dist: python-dateutil (<3.0.0,>=2.1)
Requires-Dist: docutils (>=0.10)
Requires-Dist: pyyaml (>=5.3.1)
Requires-Dist: ordereddict (==1.1) ; python_version=="2.6"
Requires-Dist: simplejson (==3.3.0) ; python_version=="2.6"
